dtpyftp/__init__.py
dtpyftp/client.py
dtpyftp/file_folder.py
dtpyftp-1.0.0.dist-info/METADATA
dtpyftp-1.0.0.dist-info/WHEEL
dtpyftp-1.0.0.dist-info/RECORD
