Metadata-Version: 2.3
Name: dtpyftp
Version: 1.0.0
Summary: A package that has different utils, wrappers, and functions.
License: MIT
Author: Reza Shirazi
Author-email: reza@datgate.com
Requires-Python: >=3.11.9,<3.12.0
Classifier: License :: OSI Approved :: MIT License
Classifier: Programming Language :: Python :: 3
Requires-Dist: paramiko (>=3.5.1,<3.6.0)
Requires-Dist: python-dateutil (>=2.9.0,<2.10.0)
